{"next":"","back":{"prev":"item","id":"68","namevi":"XE M\u00c1Y \u0110I\u1ec6N 3 B\u00c1NH","nameen":""},"data":[{"namevi":"XE M\u00c1Y \u0110I\u1ec6N 3 B\u00c1NH E-WHEELS","nameen":"","slugvi":"xe-may-dien-3-banh-e-wheels","slugen":"","id":"2167","id_list":"7","id_cat":"68","photo":"e-wheels-369x137-98661.png"},{"namevi":"XE M\u00c1Y \u0110I\u1ec6N 3 B\u00c1NH TERRA MOTORS","nameen":"","slugvi":"xe-may-dien-3-banh-terra-motors","slugen":"","id":"2168","id_list":"7","id_cat":"68","photo":"terra-motors-86723.png"},{"namevi":"XE M\u00c1Y \u0110I\u1ec6N 3 B\u00c1NH EAGLE","nameen":"","slugvi":"xe-may-dien-3-banh-eagle","slugen":"","id":"2169","id_list":"7","id_cat":"68","photo":"eagle-33458.png"},{"namevi":"XE M\u00c1Y \u0110I\u1ec6N 3 B\u00c1NH YADEA","nameen":"","slugvi":"xe-may-dien-3-banh-yadea","slugen":"","id":"2170","id_list":"7","id_cat":"68","photo":"yadea-54790.png"},{"namevi":"XE M\u00c1Y \u0110I\u1ec6N 3 B\u00c1NH LIXI","nameen":"","slugvi":"xe-may-dien-3-banh-lixi","slugen":"","id":"2171","id_list":"7","id_cat":"68","photo":"lixi-300-x-300-74785.png"},{"namevi":"XE M\u00c1Y \u0110I\u1ec6N 3 B\u00c1NH DOOHAN","nameen":"","slugvi":"xe-may-dien-3-banh-doohan","slugen":"","id":"2172","id_list":"7","id_cat":"68","photo":"doohan-86267.png"},{"namevi":"XE M\u00c1Y \u0110I\u1ec6N 3 B\u00c1NH KH\u00c1C","nameen":"","slugvi":"xe-may-dien-3-banh-khac","slugen":"","id":"2173","id_list":"7","id_cat":"68","photo":"xe-khac-54846.jpg"}]}