{"next":"","back":{"prev":"item","id":"92","namevi":"M\u00c1Y \u0110\u1ea6M B\u00c0N","nameen":""},"data":[{"namevi":"M\u00c1Y \u0110\u1ea6M B\u00c0N CHI\u1ebeT GIANG","nameen":"","slugvi":"may-dam-ban-chiet-giang","slugen":"","id":"2267","id_list":"4","id_cat":"92","photo":""},{"namevi":"M\u00c1Y \u0110\u1ea6M B\u00c0N VIFUCO","nameen":"","slugvi":"may-dam-ban-vifuco","slugen":"","id":"2268","id_list":"4","id_cat":"92","photo":""},{"namevi":"M\u00c1Y \u0110\u1ea6M B\u00c0N MIKASA","nameen":"","slugvi":"may-dam-ban-mikasa","slugen":"","id":"2269","id_list":"4","id_cat":"92","photo":""},{"namevi":"M\u00c1Y \u0110\u1ea6M B\u00c0N TACOM","nameen":"","slugvi":"may-dam-ban-tacom","slugen":"","id":"2270","id_list":"4","id_cat":"92","photo":""},{"namevi":"M\u00c1Y \u0110\u1ea6M B\u00c0N CONMEC","nameen":"","slugvi":"may-dam-ban-conmec","slugen":"","id":"2271","id_list":"4","id_cat":"92","photo":""},{"namevi":"M\u00c1Y \u0110\u1ea6M B\u00c0N HONDA","nameen":"","slugvi":"may-dam-ban-honda","slugen":"","id":"2272","id_list":"4","id_cat":"92","photo":""},{"namevi":"M\u00c1Y \u0110\u1ea6M B\u00c0N KH\u00c1C","nameen":"","slugvi":"may-dam-ban-khac","slugen":"","id":"2273","id_list":"4","id_cat":"92","photo":""}]}