[{"id":"9606","id_region":"3","id_city":"54","id_district":"659","name":"Th\u1ecb tr\u1ea5n Tr\u00e0 C\u00fa"},{"id":"9607","id_region":"3","id_city":"54","id_district":"659","name":"Th\u1ecb tr\u1ea5n \u0110\u1ecbnh An"},{"id":"9608","id_region":"3","id_city":"54","id_district":"659","name":"X\u00e3 Ph\u01b0\u1edbc H\u01b0ng"},{"id":"9609","id_region":"3","id_city":"54","id_district":"659","name":"X\u00e3 T\u1eadp S\u01a1n"},{"id":"9610","id_region":"3","id_city":"54","id_district":"659","name":"X\u00e3 T\u00e2n S\u01a1n"},{"id":"9611","id_region":"3","id_city":"54","id_district":"659","name":"X\u00e3 An Qu\u1ea3ng H\u1eefu"},{"id":"9612","id_region":"3","id_city":"54","id_district":"659","name":"X\u00e3 L\u01b0u Nghi\u1ec7p Anh"},{"id":"9613","id_region":"3","id_city":"54","id_district":"659","name":"X\u00e3 Ng\u00e3i Xuy\u00ean"},{"id":"9614","id_region":"3","id_city":"54","id_district":"659","name":"X\u00e3 Kim S\u01a1n"},{"id":"9615","id_region":"3","id_city":"54","id_district":"659","name":"X\u00e3 Thanh S\u01a1n"},{"id":"9616","id_region":"3","id_city":"54","id_district":"659","name":"X\u00e3 H\u00e0m Giang"},{"id":"9617","id_region":"3","id_city":"54","id_district":"659","name":"X\u00e3 H\u00e0m T\u00e2n"},{"id":"9618","id_region":"3","id_city":"54","id_district":"659","name":"X\u00e3 \u0110\u1ea1i An"},{"id":"9619","id_region":"3","id_city":"54","id_district":"659","name":"X\u00e3 \u0110\u1ecbnh An"},{"id":"9620","id_region":"3","id_city":"54","id_district":"659","name":"X\u00e3 Ng\u1ecdc Bi\u00ean"},{"id":"9621","id_region":"3","id_city":"54","id_district":"659","name":"X\u00e3 Long Hi\u1ec7p"},{"id":"9622","id_region":"3","id_city":"54","id_district":"659","name":"X\u00e3 T\u00e2n Hi\u1ec7p"}]