[{"id":"8545","id_region":"3","id_city":"48","id_district":"585","name":"X\u00e3 Gia T\u00e2n 1"},{"id":"8546","id_region":"3","id_city":"48","id_district":"585","name":"X\u00e3 Gia T\u00e2n 2"},{"id":"8547","id_region":"3","id_city":"48","id_district":"585","name":"X\u00e3 Gia T\u00e2n 3"},{"id":"8548","id_region":"3","id_city":"48","id_district":"585","name":"X\u00e3 Gia Ki\u1ec7m"},{"id":"8549","id_region":"3","id_city":"48","id_district":"585","name":"X\u00e3 Quang Trung"},{"id":"8550","id_region":"3","id_city":"48","id_district":"585","name":"X\u00e3 B\u00e0u H\u00e0m 2"},{"id":"8551","id_region":"3","id_city":"48","id_district":"585","name":"X\u00e3 H\u01b0ng L\u1ed9c"},{"id":"8552","id_region":"3","id_city":"48","id_district":"585","name":"X\u00e3 L\u1ed9 25"},{"id":"8553","id_region":"3","id_city":"48","id_district":"585","name":"X\u00e3 Xu\u00e2n Thi\u1ec7n"},{"id":"8554","id_region":"3","id_city":"48","id_district":"585","name":"Th\u1ecb tr\u1ea5n D\u1ea7u Gi\u00e2y"}]