[{"id":"9089","id_region":"3","id_city":"51","id_district":"629","name":"Th\u1ecb tr\u1ea5n \u0110\u00f4ng Th\u00e0nh"},{"id":"9090","id_region":"3","id_city":"51","id_district":"629","name":"X\u00e3 M\u1ef9 Qu\u00fd \u0110\u00f4ng"},{"id":"9091","id_region":"3","id_city":"51","id_district":"629","name":"X\u00e3 M\u1ef9 Th\u1ea1nh B\u1eafc"},{"id":"9092","id_region":"3","id_city":"51","id_district":"629","name":"X\u00e3 M\u1ef9 Qu\u00fd T\u00e2y"},{"id":"9093","id_region":"3","id_city":"51","id_district":"629","name":"X\u00e3 M\u1ef9 Th\u1ea1nh T\u00e2y"},{"id":"9094","id_region":"3","id_city":"51","id_district":"629","name":"X\u00e3 M\u1ef9 Th\u1ea1nh \u0110\u00f4ng"},{"id":"9095","id_region":"3","id_city":"51","id_district":"629","name":"X\u00e3 B\u00ecnh Th\u00e0nh"},{"id":"9096","id_region":"3","id_city":"51","id_district":"629","name":"X\u00e3 B\u00ecnh H\u00f2a B\u1eafc"},{"id":"9097","id_region":"3","id_city":"51","id_district":"629","name":"X\u00e3 B\u00ecnh H\u00f2a H\u01b0ng"},{"id":"9098","id_region":"3","id_city":"51","id_district":"629","name":"X\u00e3 B\u00ecnh H\u00f2a Nam"},{"id":"9099","id_region":"3","id_city":"51","id_district":"629","name":"X\u00e3 M\u1ef9 B\u00ecnh"}]