[{"id":"6116","id_region":"2","id_city":"30","id_district":"339","name":"Th\u1ecb tr\u1ea5n Khe Sanh"},{"id":"6117","id_region":"2","id_city":"30","id_district":"339","name":"Th\u1ecb tr\u1ea5n Lao B\u1ea3o"},{"id":"6118","id_region":"2","id_city":"30","id_district":"339","name":"X\u00e3 H\u01b0\u1edbng L\u1eadp"},{"id":"6119","id_region":"2","id_city":"30","id_district":"339","name":"X\u00e3 H\u01b0\u1edbng Vi\u1ec7t"},{"id":"6120","id_region":"2","id_city":"30","id_district":"339","name":"X\u00e3 H\u01b0\u1edbng Ph\u00f9ng"},{"id":"6121","id_region":"2","id_city":"30","id_district":"339","name":"X\u00e3 H\u01b0\u1edbng S\u01a1n"},{"id":"6122","id_region":"2","id_city":"30","id_district":"339","name":"X\u00e3 H\u01b0\u1edbng Linh"},{"id":"6123","id_region":"2","id_city":"30","id_district":"339","name":"X\u00e3 T\u00e2n H\u1ee3p"},{"id":"6124","id_region":"2","id_city":"30","id_district":"339","name":"X\u00e3 H\u01b0\u1edbng T\u00e2n"},{"id":"6125","id_region":"2","id_city":"30","id_district":"339","name":"X\u00e3 T\u00e2n Th\u00e0nh"},{"id":"6126","id_region":"2","id_city":"30","id_district":"339","name":"X\u00e3 T\u00e2n Long"},{"id":"6127","id_region":"2","id_city":"30","id_district":"339","name":"X\u00e3 T\u00e2n L\u1eadp"},{"id":"6128","id_region":"2","id_city":"30","id_district":"339","name":"X\u00e3 T\u00e2n Li\u00ean"},{"id":"6129","id_region":"2","id_city":"30","id_district":"339","name":"X\u00e3 H\u00fac"},{"id":"6130","id_region":"2","id_city":"30","id_district":"339","name":"X\u00e3 Thu\u1eadn"},{"id":"6131","id_region":"2","id_city":"30","id_district":"339","name":"X\u00e3 H\u01b0\u1edbng L\u1ed9c"},{"id":"6132","id_region":"2","id_city":"30","id_district":"339","name":"X\u00e3 Ba T\u1ea7ng"},{"id":"6133","id_region":"2","id_city":"30","id_district":"339","name":"X\u00e3 Thanh"},{"id":"6134","id_region":"2","id_city":"30","id_district":"339","name":"X\u00e3  A D\u01a1i"},{"id":"6135","id_region":"2","id_city":"30","id_district":"339","name":"X\u00e3 L\u00eca"},{"id":"6136","id_region":"2","id_city":"30","id_district":"339","name":"X\u00e3 Xy"}]